{"accuracy": 0.6980796586059744, "classifier": {"model": "Neural net", "param": {"activation2": "leaky relu", "activation3": "relu", "activation4": "sigmoid", "batch_size": 64, "dropout_prob": 0.49726538452237096, "epochs": 8, "layer2": "yes", "layer2_dropout": "no", "layer3": "no", "layer3_dropout": "no", "layer4": "no", "layer4_dropout": "yes", "learning_rate": 0.003250438243469697, "neurons_input": 768, "neurons_layer2": 166, "neurons_layer3": 126, "neurons_layer4": 16, "neurons_output": 4, "optimizer": "Adamax"}}, "senses": [{"name": "('room', 'chambre', 'cuartar')", "ratio": 0.22818791946308725}, {"name": "('room', 'chambre', 'habitaci\u00f3n')", "ratio": 0.697986577181208}, {"name": "('room', 'salle', 'sal\u00f3n')", "ratio": 0.0738255033557047}], "total": 149, "number_of_senses": 4}